{"id":"20140307031159256-cazf-A3HV3LXW29N30Q-0.4.3","wid0":"cazf","wid1":"A3HV3LXW29N30Q","msgs":[{"text":"What's up, doc?","wid":"cazf","suggestions":[{"txt":"What's up, doc?","deriv":"similarity"},{"txt":"Hi!","deriv":"manual"},{"txt":"Why did the chicken cross the road?","deriv":"manual"},{"txt":"Knock knock!","deriv":"manual"}]},{"text":"I would rather not comment on that","wid":"A3HV3LXW29N30Q","suggestions":[{"txt":"\"On a different note, how's the weather?\" your mom","deriv":"similarity"},{"txt":"I dunno","deriv":"manual"},{"txt":"I would rather not comment on that","deriv":"manual"},{"txt":"stop asking me that!","deriv":"manual"}]},{"text":"Can't think of anything funny to say","wid":"cazf","suggestions":[{"txt":"Can't think of anything funny to say","deriv":"similarity"},{"txt":"On a different note, how's the weather?","deriv":"similarity"},{"txt":"Hi!","deriv":"similarity"}]},{"text":"What if I type something very long? What will happen then will it wrap to the next line?","wid":"A3HV3LXW29N30Q","suggestions":[{"txt":"cows go","deriv":"similarity"},{"txt":"What if I type something very long? What will happen then will it wrap to the next line?","deriv":"similarity"},{"txt":"What's up, doc?","deriv":"similarity"},{"txt":"On a different note, how's the weather?","deriv":"manual"}]},{"text":"I dunno","wid":"cazf","suggestions":[{"txt":"stop asking me that!","deriv":"similarity"},{"txt":"I dunno","deriv":"manual"},{"txt":"I would rather not comment on that","deriv":"manual"}]},{"text":"attempting it now, apparently the very long message i sent before was not long enough to work. Lets be committed to making it happen.","wid":"A3HV3LXW29N30Q","suggestions":[{"txt":"What's up, doc?","deriv":"similarity"},{"txt":"On a different note, how's the weather?","deriv":"similarity"},{"txt":"\"I dunno\" your mom","deriv":"similarity"}]}],"startMS":1394161919256,"elapsedMS":127270}