{"id":"20140701204219527-A1XQPDHAN5IY0R-A166A2M31CW2C7-0.4.3","wid0":"A1XQPDHAN5IY0R","wid1":"A166A2M31CW2C7","msgs":[{"text":"Why did the chicken cross the road?","wid":"A1XQPDHAN5IY0R","suggestions":[{"txt":"Hi! What's your name?","deriv":"name-question"},{"txt":"Why did the chicken cross the road?","deriv":"manual"},{"txt":"Where are you from?","deriv":"where-question"},{"txt":"Knock knock!","deriv":"KnockKnock-line1"}],"gotHa":0}],"curSuggs":[{"txt":"Why did the chicken cross the ride?","deriv":"AutoCorrect"},{"txt":"I dunno","deriv":"manual"},{"txt":"I would rather not comment on that","deriv":"manual"},{"txt":"stop asking me that!","deriv":"manual"}],"cntHa":[0,0],"startMS":1404247339527,"elapsedMS":15674}