{"id":"20140701204823853-A3TUN250T19AUM-A14PFRHG0A2YY9-0.4.3","wid0":"A3TUN250T19AUM","wid1":"A14PFRHG0A2YY9","msgs":[{"text":"Hello bubbles, whats popping?","wid":"A14PFRHG0A2YY9","suggestions":[{"txt":"Hi! What's your name?","deriv":"name-question"},{"txt":"Why did the chicken cross the road?","deriv":"manual"},{"txt":"Where are you from?","deriv":"where-question"},{"txt":"Knock knock!","deriv":"KnockKnock-line1"}],"gotHa":0},{"text":"to get to the other side?","wid":"A3TUN250T19AUM","suggestions":[{"txt":"I would rather not comment on that","deriv":"manual"},{"txt":"stop asking me that!","deriv":"manual"},{"txt":"nothing","deriv":"simsimi"},{"txt":"Just some boys gave me their phone numbers.","deriv":"Friends","conf":0.5}],"gotHa":0},{"text":"Hey, come on now!","wid":"A14PFRHG0A2YY9","suggestions":[{"txt":"<div class =\"meme-block\" style='display:inline-block;position:relative; font-family: \"times\", \"serif\", joseph, \"Marker Felt\", Sans; font-size: 60px;'>\n<img src=\"Images/joseph.png\" class=\"meme-pic joseph\" />\n<div style=\"position:absolute;color: white;width: 400px;text-align: center;font-size: 30px;top: 20px;margin-left: auto;margin-right: auto;\">TO ACQUIRE TO </div>\n<div style=\"position:absolute;color: white;width: 400px;text-align: center;font-size: 30px;bottom: 20px;margin-left: auto;margin-right: auto;\">YE OYER SIDE? </div>\n</div>","deriv":"meme-Joseph","conf":0},{"txt":"Hey, come on now!","deriv":"Friends","conf":0.7071067811865475},{"txt":"to get to the other ride?","deriv":"AutoCorrect"},{"txt":"I dunno","deriv":"manual"}],"gotHa":0},{"text":"What a good day it is to puke my guts out.","wid":"A14PFRHG0A2YY9","suggestions":[{"txt":"<div style='display:inline-block;position:relative; font-family: \"Comic Sans MS\", \"Comic Sans\", doge, \"Marker Felt\", Sans; font-size: 15px;'>\n<img src=\"Images/doge.png\" class=\"meme-pic\" width=\"300\" height=\"300\" />\n<div style=\"position:absolute;color:red;left:84.39165386091918px;top:80.51890316605568px;\">WOW</div>\n<div style=\"position:absolute;color:red;left:96.27329975087196px;top:124.43483692780137px;\">such hey</div>\n<div style=\"position:absolute;color:red;right:154.5837031044066px;bottom:176.69014844298363px;\"> so come</div>\n<div style=\"position:absolute;color:yellow;right:30.3891080589965px;bottom:51.237889017909765px;\">much on.&nbsp</div>\n</div>","deriv":"meme-doge"},{"txt":"Hey!","deriv":"Friends","conf":1},{"txt":"Hey, come john now!","deriv":"AutoCorrect"},{"txt":"come on baby","deriv":"simsimi"}],"gotHa":0},{"text":"thats not very funny","wid":"A3TUN250T19AUM","suggestions":[{"txt":"What a good day it is to puke bi guts out.","deriv":"AutoCorrect"},{"txt":"\"What a good day it is to puke my guts out.\" your mom","deriv":"manual"},{"txt":"yes,it is","deriv":"simsimi"},{"txt":"What? I'm just said.","deriv":"Friends","conf":0.5163977794943222}],"gotHa":0},{"text":"knock knock","wid":"A3TUN250T19AUM","suggestions":[{"txt":"<div style='display:inline-block;position:relative; font-family: \"Comic Sans MS\", \"Comic Sans\", doge, \"Marker Felt\", Sans; font-size: 15px;'>\n<img src=\"Images/doge.png\" class=\"meme-pic\" width=\"300\" height=\"300\" />\n<div style=\"position:absolute;color:red;left:189.55368940439075px;bottom:116.58268738724291px;\">WOW</div>\n<div style=\"position:absolute;color:indigo;right:140.39069305825979px;bottom:73.56380036752671px;\">such thats</div>\n<div style=\"position:absolute;color:green;right:48.725632519461215px;top:125.10945000406355px;\"> so not</div>\n<div style=\"position:absolute;color:darkcyan;right:108.39326460566372px;bottom:32.59920541383326px;\">much very.&nbsp</div>\n</div>","deriv":"meme-doge"},{"txt":"Well, I snapped! Okay? You weren't taking the class seriously.","deriv":"Friends","conf":1.0000000000000002},{"txt":"thats not fairy funny","deriv":"AutoCorrect"},{"txt":"sorry","deriv":"simsimi"}],"gotHa":0},{"text":"you're supposed to say whose there?","wid":"A3TUN250T19AUM","suggestions":[{"txt":"Quick, take off your dress, he won't notice the bed.","deriv":"Friends","conf":1},{"txt":"\"knock knock\" your dad","deriv":"manual"},{"txt":"Who there","deriv":"simsimi"},{"txt":"stop asking me that!","deriv":"similarity","conf":0.9244327134385465}],"gotHa":0},{"text":"oh, who there","wid":"A14PFRHG0A2YY9","suggestions":[{"txt":"<div class =\"meme-block\" style='display:inline-block;position:relative; font-family: \"times\", \"serif\", joseph, \"Marker Felt\", Sans; font-size: 60px;'>\n<img src=\"Images/joseph.png\" class=\"meme-pic joseph\" />\n<div style=\"position:absolute;color: white;width: 400px;text-align: center;font-size: 30px;top: 20px;margin-left: auto;margin-right: auto;\">THOU'RE SUPPOSED TO </div>\n<div style=\"position:absolute;color: white;width: 400px;text-align: center;font-size: 30px;bottom: 20px;margin-left: auto;margin-right: auto;\">SAY WHOSE THERE? </div>\n</div>","deriv":"meme-Joseph","conf":0},{"txt":"you're supposed woo say whose there?","deriv":"AutoCorrect"},{"txt":"I would rather not comment on that","deriv":"manual"},{"txt":"stop asking me that!","deriv":"manual"}],"gotHa":0},{"text":"woo","wid":"A3TUN250T19AUM","suggestions":[{"txt":"don't, don't you dare, don't, don't. Tell him I cook.","deriv":"Friends","conf":1},{"txt":"oh, woo there","deriv":"AutoCorrect"},{"txt":"\"oh, who there\" your mom","deriv":"manual"},{"txt":"you sound like christian novelli ♥","deriv":"simsimi"}],"gotHa":0},{"text":"... that's what she said","wid":"A14PFRHG0A2YY9","suggestions":[{"txt":"<div style='display:inline-block;position:relative; font-family: \"Comic Sans MS\", \"Comic Sans\", doge, \"Marker Felt\", Sans; font-size: 15px;'>\n<img src=\"Images/doge.png\" class=\"meme-pic\" width=\"300\" height=\"300\" />\n<div style=\"position:absolute;color:green;left:144.1544193327427px;bottom:69.3662021420896px;\">WOW</div>\n<div style=\"position:absolute;color:crimson;right:87.25652629695833px;top:182.04274224769324px;\">such joke</div>\n<div style=\"position:absolute;color:yellow;left:111.00048111006618px;top:97.65549909509718px;\">so laugh</div>\n<div style=\"position:absolute;color:crimson;left:70.90356379933655px;bottom:114.24525320716202px;\">much funny.</div>\n</div>","deriv":"meme-doge"},{"txt":"... that's what she said","deriv":"TWSS-answer","conf":1},{"txt":"I can't believe you did that!","deriv":"Friends","conf":1},{"txt":"Muscle manWOOO","deriv":"simsimi"}],"gotHa":0},{"text":"tell me about your ingrown toes nails","wid":"A14PFRHG0A2YY9","suggestions":[{"txt":"Remember I had to leave the room the other day when you had that roast chicken?","deriv":"Friends","conf":1},{"txt":"... that's what she bed","deriv":"AutoCorrect"},{"txt":"\"... that's what she said\" your dad","deriv":"manual"},{"txt":"?","deriv":"simsimi"}],"gotHa":0},{"text":"you're killing my punch line!","wid":"A3TUN250T19AUM","suggestions":[{"txt":"tell me about whore ingrown toes nails","deriv":"AutoCorrect"},{"txt":"\"tell me about your ingrown toes nails\" your dad","deriv":"manual"},{"txt":"eww is it bloody?","deriv":"simsimi"},{"txt":"Just...please tell him.","deriv":"Friends","conf":0.5}],"gotHa":0},{"text":"umm eww","wid":"A3TUN250T19AUM","suggestions":[{"txt":"you're killing my punch loin!","deriv":"AutoCorrect"},{"txt":"\"you're killing my punch line!\" your dad","deriv":"manual"},{"txt":"Look, I'm not saying that you should magically forgive me! But you're not perfect! You've made some errors in judgment too!","deriv":"Friends","conf":0.5669467095138409},{"txt":"All i wanted was you","deriv":"simsimi"}],"gotHa":0},{"text":"you're supposed to say \"woo who?'","wid":"A3TUN250T19AUM","suggestions":[{"txt":"So Pheebs, are you gonna go back out there or what?","deriv":"Friends","conf":0.7071067811865475},{"txt":"\"umm eww\" your mom","deriv":"manual"},{"txt":"I'm sorry.","deriv":"simsimi"},{"txt":"said the blind man","deriv":"similarity","conf":0.9234972654768785}],"gotHa":0},{"text":"what about your shankers on your barb","wid":"A14PFRHG0A2YY9","suggestions":[{"txt":"you're supposed to say \"woo woo?'","deriv":"AutoCorrect"},{"txt":"\"you're supposed to say \"woo who?'\" your mom","deriv":"manual"},{"txt":"Hey!","deriv":"Friends","conf":0.5773502691896258},{"txt":"Oh! Sorry. I'll say that, next time.","deriv":"simsimi"}],"gotHa":0},{"text":"I was trying to help out a squirrel.","wid":"A3TUN250T19AUM","suggestions":[{"txt":"what about whore shankers on your barb","deriv":"AutoCorrect"},{"txt":"\"what about your shankers on your barb\" your dad","deriv":"manual"},{"txt":"why would you do that","deriv":"simsimi"},{"txt":"I was trying to help out a squirrel.","deriv":"Friends","conf":0.35355339059327373}],"gotHa":0},{"text":"what on the what?!","wid":"A3TUN250T19AUM","suggestions":[{"txt":"You were trying to eat it!","deriv":"Friends","conf":1},{"txt":"it's all slimy cause I was sucking on it.","deriv":"TWSS-story"},{"txt":"I was trying to hell out a squirrel.","deriv":"AutoCorrect"},{"txt":"I'm gonna bread a squirrel and shark to make a man eating squirrel.","deriv":"simsimi"}],"gotHa":0},{"text":"do they ooze puss","wid":"A14PFRHG0A2YY9","suggestions":[{"txt":"<div class =\"meme-block\" style='display:inline-block;position:relative; font-family: \"times\", \"serif\", joseph, \"Marker Felt\", Sans; font-size: 60px;'>\n<img src=\"Images/joseph.png\" class=\"meme-pic joseph\" />\n<div style=\"position:absolute;color: white;width: 400px;text-align: center;font-size: 30px;top: 20px;margin-left: auto;margin-right: auto;\">WHAT ON </div>\n<div style=\"position:absolute;color: white;width: 400px;text-align: center;font-size: 30px;bottom: 20px;margin-left: auto;margin-right: auto;\">YE WHAT?! </div>\n</div>","deriv":"meme-Joseph","conf":0},{"txt":"what john the what?!","deriv":"AutoCorrect"},{"txt":"\"what on the what?!\" your dad","deriv":"manual"},{"txt":"You tell me...","deriv":"simsimi"}],"gotHa":0},{"text":"i thought this was supposed to be funny not gross","wid":"A3TUN250T19AUM","suggestions":[{"txt":"You know how that thing pops up? It was very little.","deriv":"TWSS-story"},{"txt":"woo they ooze puss","deriv":"AutoCorrect"},{"txt":"Yes , only if it taste like water ..","deriv":"simsimi"},{"txt":"... that's what she said","deriv":"TWSS-answer","conf":0.25}],"gotHa":0}],"curSuggs":[{"txt":"i thought this was supposed to pee funny not gross","deriv":"AutoCorrect"},{"txt":"\"i thought this was supposed to be funny not gross\" your dad","deriv":"manual"},{"txt":"Well, get it off now!","deriv":"Friends","conf":0.6324555320336759},{"txt":"Idgaf","deriv":"simsimi"}],"cntHa":[0,1],"startMS":1404247703853,"elapsedMS":313183,"dead":true}