{"id":"20140323154915081-adum-yo-0.4.3","wid0":"adum","wid1":"yo","msgs":[{"text":"Hi!","wid":"adum","suggestions":[{"txt":"On a different note, how's the weather?","deriv":"similarity"},{"txt":"Hi!","deriv":"manual"},{"txt":"Why did the chicken cross the road?","deriv":"manual"},{"txt":"Knock knock!","deriv":"manual"}],"isHa":false},{"text":"<div style=\"display:inline-block;position:relative; font-family: &quot;Comic Sans MS&quot;, &quot;Comic Sans&quot;, doge, &quot;Marker Felt&quot;, Sans; font-size: 15px;\">\n<img src=\"Images/doge.png\" class=\"meme-pic\" width=\"300\" height=\"300\">\n<div style=\"position:absolute;color:indigo;left:188.38915614131838px;top:169.44934193696827px;\">WOW</div>\n<div style=\"position:absolute;color:fuchsia;right:191.59329419676214px;bottom:149.38169169891626px;\">such joke</div>\n<div style=\"position:absolute;color:red;right:58.94110353849828px;top:72.17160753160715px;\">so laugh</div>\n<div style=\"position:absolute;color:navy;right:63.95911741722375px;bottom:32.698057137429714px;\">much funny.</div>\n</div>","wid":"yo","suggestions":[{"txt":"I dunno","deriv":"similarity"},{"txt":"On a different note, how's the weather?","deriv":"similarity"},{"txt":"Knock knock!","deriv":"similarity"},{"txt":"<div style='display:inline-block;position:relative; font-family: \"Comic Sans MS\", \"Comic Sans\", doge, \"Marker Felt\", Sans; font-size: 15px;'>\n<img src=\"Images/doge.png\" class=\"meme-pic\" width=\"300\" height=\"300\" />\n<div style=\"position:absolute;color:indigo;left:188.38915614131838px;top:169.44934193696827px;\">WOW</div>\n<div style=\"position:absolute;color:fuchsia;right:191.59329419676214px;bottom:149.38169169891626px;\">such joke</div>\n<div style=\"position:absolute;color:red;right:58.94110353849828px;top:72.17160753160715px;\">so laugh</div>\n<div style=\"position:absolute;color:navy;right:63.95911741722375px;bottom:32.698057137429714px;\">much funny.</div>\n</div>","deriv":"manual"}],"isHa":false},{"text":"HaHa","wid":"adum","suggestions":[{"txt":"On a different note, how's the weather?","deriv":"similarity"},{"txt":"I dunno","deriv":"similarity"},{"txt":"You talkin' to me?","deriv":"similarity"},{"txt":"<div style='display:inline-block;position:relative; font-family: \"Comic Sans MS\", \"Comic Sans\", doge, \"Marker Felt\", Sans; font-size: 15px;'>\n<img src=\"Images/doge.png\" class=\"meme-pic\" width=\"300\" height=\"300\" />\n<div style=\"position:absolute;color:red;left:179.73129356000572px;top:180.90362580679357px;\">WOW</div>\n<div style=\"position:absolute;color:red;left:70.88385907653719px;bottom:181.81403820589185px;\">such joke</div>\n<div style=\"position:absolute;color:crimson;left:34.60988589283079px;top:76.1038597645238px;\">so laugh</div>\n<div style=\"position:absolute;color:maroon;right:58.92915333341807px;top:107.36782479286194px;\">much funny.</div>\n</div>","deriv":"manual"}],"isHa":true}],"startMS":1395589755081,"elapsedMS":10302927}