{"id":"20140626182143179-mwen1-mwen2-0.4.3","wid0":"mwen1","wid1":"mwen2","msgs":[{"text":"Knock knock!","wid":"mwen1","isHa":false},{"text":"HaHa","wid":"mwen2","isHa":true},{"text":"HaHaHa","wid":"mwen2","isHa":true}],"curSuggs":[{"txt":"\"HaHaHa\" your mom","deriv":"manual"},{"txt":"cows go who?","deriv":"similarity","conf":0.4919513198061896},{"txt":"Who's there?","deriv":"similarity","conf":0.2770542502742654},{"txt":"no! cows go moo!","deriv":"similarity","conf":0.2011392049637706}],"cntHa":[0,0],"startMS":1403806903179,"elapsedMS":11259}